atlas248nb/__init__.py
atlas248nb-0.1.dist-info/LICENCE
atlas248nb-0.1.dist-info/METADATA
atlas248nb-0.1.dist-info/WHEEL
atlas248nb-0.1.dist-info/top_level.txt
atlas248nb-0.1.dist-info/RECORD
