Metadata-Version: 2.1
Name: atlas248nb
Version: 0.1
Summary: Full usage report of notebooks on the atlas-248 private cluster
Home-page: UNKNOWN
Author: Matteo Zennaro
Author-email: matteo.zennaro90@gmail.com
License: UNKNOWN
Platform: UNKNOWN
Classifier: Programming Language :: Python :: 3
Classifier: License :: OSI Approved :: MIT License
Classifier: Operating System :: OS Independent
